README.rst
setup.cfg
setup.py
django_hitcounter/__init__.py
django_hitcounter/apps.py
django_hitcounter/managers.py
django_hitcounter/models.py
django_hitcounter/migrations/0001_initial.py
django_hitcounter/migrations/__init__.py
djangohitcounter.egg-info/PKG-INFO
djangohitcounter.egg-info/SOURCES.txt
djangohitcounter.egg-info/dependency_links.txt
djangohitcounter.egg-info/top_level.txt
tests/test_app/__init__.py
tests/test_app/apps.py
tests/test_app/models.py
tests/test_app/tests.py
tests/test_app/migrations/0001_initial.py
tests/test_app/migrations/__init__.py