Metadata-Version: 1.1
Name: djangohitcounter
Version: 0.2
Summary: Pretty simple hit counter for Django ORM objects
Home-page: https://github.com/DirectlineDev/django-hitcounter
Author: Anton Kuzmichev
Author-email: assargin@gmail.com
License: Apache 2.0
Download-URL: https://github.com/DirectlineDev/django-hitcounter/archive/master.zip
Keywords: django,hits,counter,hits counter,hitcounter
Platform: UNKNOWN
Classifier: Development Status :: 4 - Beta
Classifier: Framework :: Django
Classifier: Framework :: Django :: 1.7
Classifier: Framework :: Django :: 1.8
Classifier: Intended Audience :: Developers
Classifier: License :: OSI Approved :: Apache Software License
Classifier: Operating System :: OS Independent
Classifier: Programming Language :: Python
Classifier: Programming Language :: Python :: 2
Classifier: Programming Language :: Python :: 2.7
Classifier: Programming Language :: Python :: 3
Classifier: Programming Language :: Python :: 3.4
